buildhat/__init__.py
buildhat/color.py
buildhat/colordistance.py
buildhat/devices.py
buildhat/distance.py
buildhat/exc.py
buildhat/force.py
buildhat/hat.py
buildhat/light.py
buildhat/matrix.py
buildhat/motors.py
buildhat/serinterface.py
buildhat/wedo.py
buildhat/data/firmware.bin
buildhat/data/signature.bin
buildhat/data/version
buildhat-0.9.0.dist-info/licenses/LICENSE
buildhat-0.9.0.dist-info/METADATA
buildhat-0.9.0.dist-info/WHEEL
buildhat-0.9.0.dist-info/top_level.txt
buildhat-0.9.0.dist-info/RECORD
