Metadata-Version: 2.4
Name: buildhat
Version: 0.9.0
Summary: Build HAT Python library
Home-page: https://github.com/RaspberryPiFoundation/python-build-hat
Author: Raspberry Pi Foundation
Author-email: web@raspberrypi.org
License: MIT
Project-URL: Bug Tracker, https://github.com/RaspberryPiFoundation/python-build-hat/issues
Requires-Python: >=3.7
License-File: LICENSE
Requires-Dist: gpiozero
Requires-Dist: pyserial
Dynamic: author
Dynamic: author-email
Dynamic: description
Dynamic: description-content-type
Dynamic: home-page
Dynamic: license
Dynamic: license-file
Dynamic: project-url
Dynamic: requires-dist
Dynamic: requires-python
Dynamic: summary
